[
  {
    "id": "post_0",
    "imageUrl": "https://ssl.pstatic.net/static/nid/membership/video_intro-8ae64dc1.png",
    "channel": "Reserve Estimation for Unconventional Resources 2012",
    "company": "Crist, White and Sanford",
    "title": "asha-stoltenberg",
    "content": "Purdyhaven",
    "thumbnailUrls": [
      "https://ssl.pstatic.net/static/nid/membership/video_intro-8ae64dc1.png",
      "https://ssl.pstatic.net/static/nid/membership/video_intro-8ae64dc1.png"
    ],
    "isLike": false,
    "likeCount": 0,
    "commentCount": 0,
    "viewCount": 70091576,
    "createdAt": 1715139336290
  },
  {
    "id": "post_1",
    "imageUrl": "https://ssl.pstatic.net/static/nid/membership/video_intro-8ae64dc1.png",
    "channel": "Reserve Estimation for Unconventional Resources 2012",
    "company": "Aufderhar-Kshlerin",
    "title": "gabriel-kiehn",
    "content": "West Port Beatriceside",
    "thumbnailUrls": [],
    "isLike": false,
    "likeCount": 1,
    "commentCount": 1,
    "viewCount": 38280222,
    "createdAt": 1715139276291
  },
  {
    "id": "post_2",
    "imageUrl": "https://ssl.pstatic.net/static/nid/membership/video_intro-8ae64dc1.png",
    "channel": "Open Networking Summit 2012",
    "company": "Graham, Haley and Kuhn",
    "title": "alexander_hayes",
    "content": "Crystelhaven",
    "thumbnailUrls": [],
    "isLike": false,
    "likeCount": 2,
    "commentCount": 2,
    "viewCount": 63793996,
    "createdAt": 1715139216291
  },
  {
    "id": "post_3",
    "imageUrl": "https://ssl.pstatic.net/static/nid/membership/video_intro-8ae64dc1.png",
    "channel": "Open Networking Summit 2012",
    "company": "DuBuque Inc",
    "title": "jeffrey.littel",
    "content": "South Lake Antoinetteton",
    "thumbnailUrls": [
      "https://ssl.pstatic.net/static/nid/membership/video_intro-8ae64dc1.png",
      "https://ssl.pstatic.net/static/nid/membership/video_intro-8ae64dc1.png"
    ],
    "isLike": false,
    "likeCount": 3,
    "commentCount": 3,
    "viewCount": 97034747,
    "createdAt": 1715139156291
  },
  {
    "id": "post_4",
    "imageUrl": "https://ssl.pstatic.net/static/nid/membership/video_intro-8ae64dc1.png",
    "channel": "LatAm Pipeline Integrity Management Summit",
    "company": "Quigley, Raynor and White",
    "title": "kunde-dayton",
    "content": "East New Florianport",
    "thumbnailUrls": [],
    "isLike": false,
    "likeCount": 4,
    "commentCount": 4,
    "viewCount": 70182428,
    "createdAt": 1715139096291
  },
  {
    "id": "post_5",
    "imageUrl": "https://ssl.pstatic.net/static/nid/membership/video_intro-8ae64dc1.png",
    "channel": "Datacentre Investment Forum",
    "company": "Roob-Hackett",
    "title": "witting.gerda",
    "content": "East Lake Cordell",
    "thumbnailUrls": [],
    "isLike": false,
    "likeCount": 5,
    "commentCount": 5,
    "viewCount": 68051655,
    "createdAt": 1715139036291
  },
  {
    "id": "post_6",
    "imageUrl": "https://ssl.pstatic.net/static/nid/membership/video_intro-8ae64dc1.png",
    "channel": "Dow Jones Global Compliance Symposium 2011",
    "company": "Hilpert-Predovic",
    "title": "harmony.mcclure",
    "content": "North Lake Claudieborough",
    "thumbnailUrls": [
      "https://ssl.pstatic.net/static/nid/membership/video_intro-8ae64dc1.png",
      "https://ssl.pstatic.net/static/nid/membership/video_intro-8ae64dc1.png"
    ],
    "isLike": false,
    "likeCount": 6,
    "commentCount": 6,
    "viewCount": 71591675,
    "createdAt": 1715138976292
  },
  {
    "id": "post_7",
    "imageUrl": "https://ssl.pstatic.net/static/nid/membership/video_intro-8ae64dc1.png",
    "channel": "Device Master Record Device History Record a requirements, contents and implementation - Webinar",
    "company": "Willms Group",
    "title": "rene-grant",
    "content": "East Lake Danberg",
    "thumbnailUrls": [],
    "isLike": false,
    "likeCount": 7,
    "commentCount": 7,
    "viewCount": 55546414,
    "createdAt": 1715138916292
  },
  {
    "id": "post_8",
    "imageUrl": "https://ssl.pstatic.net/static/nid/membership/video_intro-8ae64dc1.png",
    "channel": "Met Coke World Summit 2012",
    "company": "Klocko-Kunze",
    "title": "bailee-schinner",
    "content": "Stehrberg",
    "thumbnailUrls": [],
    "isLike": false,
    "likeCount": 8,
    "commentCount": 8,
    "viewCount": 83164473,
    "createdAt": 1715138856292
  },
  {
    "id": "post_9",
    "imageUrl": "https://ssl.pstatic.net/static/nid/membership/video_intro-8ae64dc1.png",
    "channel": "LatAm Pipeline Integrity Management Summit",
    "company": "Dickens, Monahan and Oberbrunner",
    "title": "candida-gerhold",
    "content": "Reneshire",
    "thumbnailUrls": [
      "https://ssl.pstatic.net/static/nid/membership/video_intro-8ae64dc1.png",
      "https://ssl.pstatic.net/static/nid/membership/video_intro-8ae64dc1.png"
    ],
    "isLike": false,
    "likeCount": 9,
    "commentCount": 9,
    "viewCount": 44294411,
    "createdAt": 1715138796292
  }
]